aws_automation-0.1.1.dist-info/licenses/LICENSE
cli/__init__.py
cli/__main__.py
cli/app.py
cli/headless.py
cli/flow/__init__.py
cli/flow/context.py
cli/flow/runner.py
cli/flow/steps/__init__.py
cli/flow/steps/account.py
cli/flow/steps/category.py
cli/flow/steps/profile.py
cli/flow/steps/region.py
cli/flow/steps/role.py
cli/ui/__init__.py
cli/ui/banner.py
cli/ui/console.py
cli/ui/main_menu.py
cli/ui/search.py
core/__init__.py
core/config.py
core/exceptions.py
core/filter.py
core/types.py
core/auth/__init__.py
core/auth/account.py
core/auth/auth.py
core/auth/session.py
core/auth/cache/__init__.py
core/auth/cache/cache.py
core/auth/config/__init__.py
core/auth/config/loader.py
core/auth/provider/__init__.py
core/auth/provider/base.py
core/auth/provider/sso_profile.py
core/auth/provider/sso_session.py
core/auth/provider/static.py
core/auth/types/__init__.py
core/auth/types/types.py
core/parallel/__init__.py
core/parallel/client.py
core/parallel/decorators.py
core/parallel/errors.py
core/parallel/executor.py
core/parallel/quiet.py
core/parallel/rate_limiter.py
core/parallel/types.py
core/region/__init__.py
core/region/data.py
core/region/update_regions.py
core/tools/__init__.py
core/tools/aws_categories.py
core/tools/base.py
core/tools/discovery.py
core/tools/types.py
core/tools/cache/__init__.py
core/tools/cache/path.py
core/tools/history/__init__.py
core/tools/history/favorites.py
core/tools/history/profile_groups.py
core/tools/history/recent.py
core/tools/io/__init__.py
core/tools/io/csv/__init__.py
core/tools/io/csv/handler.py
core/tools/io/excel/__init__.py
core/tools/io/excel/styles.py
core/tools/io/excel/workbook.py
core/tools/io/file/__init__.py
core/tools/io/file/io.py
core/tools/output/__init__.py
core/tools/output/builder.py
plugins/__init__.py
plugins/acm/__init__.py
plugins/acm/unused.py
plugins/apigateway/__init__.py
plugins/apigateway/unused.py
plugins/cloudformation/__init__.py
plugins/cloudformation/resource_finder.py
plugins/cloudtrail/__init__.py
plugins/cloudtrail/trail_audit.py
aws_automation-0.1.1.dist-info/METADATA
aws_automation-0.1.1.dist-info/WHEEL
aws_automation-0.1.1.dist-info/entry_points.txt
aws_automation-0.1.1.dist-info/top_level.txt
aws_automation-0.1.1.dist-info/RECORD
