Metadata-Version: 2.4
Name: aws-automation
Version: 0.1.1
Summary: AWS 운영 자동화 CLI 도구
Author-email: Euncheol Hong <where906@gmail.com>
License-Expression: MIT
Project-URL: Homepage, https://github.com/expeor/aws-automation
Project-URL: Issues, https://github.com/expeor/aws-automation/issues
Keywords: aws,automation,cli,devops,cloud
Classifier: Development Status :: 4 - Beta
Classifier: Environment :: Console
Classifier: Intended Audience :: Developers
Classifier: Intended Audience :: System Administrators
Classifier: Topic :: System :: Systems Administration
Classifier: Operating System :: OS Independent
Classifier: Programming Language :: Python :: 3
Classifier: Programming Language :: Python :: 3.10
Classifier: Programming Language :: Python :: 3.11
Classifier: Programming Language :: Python :: 3.12
Classifier: Programming Language :: Python :: 3.13
Requires-Python: >=3.10
License-File: LICENSE
Requires-Dist: boto3>=1.34.0
Requires-Dist: click>=8.1.0
Requires-Dist: rich<15.0.0,>=13.7.0
Requires-Dist: questionary>=2.0.0
Requires-Dist: openpyxl>=3.1.0
Requires-Dist: msgpack>=1.0.0
Requires-Dist: chardet>=5.2.0
Requires-Dist: python-dateutil>=2.8.0
Requires-Dist: duckdb>=1.0.0
Requires-Dist: requests>=2.31.0
Requires-Dist: pytz>=2024.1
Requires-Dist: cryptography>=42.0.0
Provides-Extra: dev
Requires-Dist: pytest>=8.0.0; extra == "dev"
Requires-Dist: pytest-cov>=5.0.0; extra == "dev"
Requires-Dist: moto>=5.0.0; extra == "dev"
Requires-Dist: ruff>=0.8.0; extra == "dev"
Requires-Dist: mypy>=1.10.0; extra == "dev"
Requires-Dist: bandit>=1.7.0; extra == "dev"
Requires-Dist: safety>=3.0.0; extra == "dev"
Requires-Dist: pre-commit>=3.8.0; extra == "dev"
Dynamic: license-file
